documentation/docs/translate.py
examples/local/benchmark.py
examples/local/question_answering.py
maritalk/__init__.py
maritalk/download.py
maritalk/start.py
maritalk/tokenizer.py
maritalk/tokenizer_model.py
maritalk/resources/api.py
maritalk/resources/local.py
maritalk-0.2.7.dist-info/licenses/LICENSE
maritalk-0.2.7.dist-info/METADATA
maritalk-0.2.7.dist-info/WHEEL
maritalk-0.2.7.dist-info/top_level.txt
maritalk-0.2.7.dist-info/RECORD
