Metadata-Version: 2.4
Name: maritalk
Version: 0.2.7
Summary: Client library for the MariTalk API
Author-email: Maritaca AI <suporte@maritaca.ai>
License: The MIT License
Project-URL: Homepage, https://github.com/maritaca-ai/maritalk-api
Project-URL: Bug Tracker, https://github.com/maritaca-ai/maritalk-api/issues
Classifier: Programming Language :: Python :: 3
Classifier: License :: OSI Approved :: MIT License
Classifier: Operating System :: OS Independent
Requires-Python: >=3.7
License-File: LICENSE
Requires-Dist: requests
Requires-Dist: tqdm
Requires-Dist: httpx
Requires-Dist: tiktoken<0.8,>=0.7
Requires-Dist: transformers
Dynamic: license-file
